monzo/__init__.py
monzo/auth.py
monzo/const.py
monzo/errors.py
monzo/monzo.py
monzo/utils.py
monzo-0.10.0.dist-info/LICENSE.md
monzo-0.10.0.dist-info/METADATA
monzo-0.10.0.dist-info/WHEEL
monzo-0.10.0.dist-info/top_level.txt
monzo-0.10.0.dist-info/RECORD
